kinematic_tracker/__init__.py
kinematic_tracker/association/__init__.py
kinematic_tracker/association/association.py
kinematic_tracker/association/association_method.py
kinematic_tracker/association/association_metric.py
kinematic_tracker/association/det_type.py
kinematic_tracker/association/g_iou_scores_aligned.py
kinematic_tracker/association/inv_out.py
kinematic_tracker/association/match_driver_base.py
kinematic_tracker/association/match_greedy.py
kinematic_tracker/association/match_hungarian.py
kinematic_tracker/association/metric_driver_base.py
kinematic_tracker/association/metric_giou_aligned.py
kinematic_tracker/association/metric_mahalanobis.py
kinematic_tracker/association/metric_mean_dim_giou.py
kinematic_tracker/association/metric_size_modulated_mahalanobis.py
kinematic_tracker/core/__init__.py
kinematic_tracker/core/creation_id.py
kinematic_tracker/core/derivative_mixer.py
kinematic_tracker/core/free_id.py
kinematic_tracker/core/giou_1d.py
kinematic_tracker/core/kalman_cv2_copy.py
kinematic_tracker/core/loose_items.py
kinematic_tracker/core/track_free_id.py
kinematic_tracker/matrices/__init__.py
kinematic_tracker/matrices/factory.py
kinematic_tracker/matrices/const_acc/__init__.py
kinematic_tracker/matrices/const_acc/fundamental.py
kinematic_tracker/matrices/const_acc/proc_cov.py
kinematic_tracker/matrices/const_jerk/__init__.py
kinematic_tracker/matrices/const_jerk/fundamental.py
kinematic_tracker/matrices/const_jerk/proc_cov.py
kinematic_tracker/matrices/const_pos/__init__.py
kinematic_tracker/matrices/const_pos/fundamental.py
kinematic_tracker/matrices/const_pos/proc_cov.py
kinematic_tracker/matrices/const_vel/__init__.py
kinematic_tracker/matrices/const_vel/fundamental.py
kinematic_tracker/matrices/const_vel/proc_cov.py
kinematic_tracker/nd/__init__.py
kinematic_tracker/nd/derivative_sorted.py
kinematic_tracker/nd/gen_kf.py
kinematic_tracker/nd/gen_x.py
kinematic_tracker/nd/gen_xz.py
kinematic_tracker/nd/precursors.py
kinematic_tracker/nd/shape.py
kinematic_tracker-17.0.1.dist-info/METADATA
kinematic_tracker-17.0.1.dist-info/WHEEL
kinematic_tracker-17.0.1.dist-info/RECORD
