Metadata-Version: 2.4
Name: kinematic-tracker
Version: 17.0.1
Summary: Tracker using kinematic Kalman filters.
Author-email: Peter Koval <pkoval@vicomtech.org>
License-Expression: MIT
Requires-Python: >=3.10
Requires-Dist: association-quality-clavia>=0.1.0
Requires-Dist: binary-classification-ratios>=0.3.0
Requires-Dist: numpy
Requires-Dist: opencv-python>=4.11.0.86
Requires-Dist: scipy>=1.15.3
